secudeps/__init__.py
secudeps/cli.py
secudeps/core.py
secudeps-0.1.0.dist-info/LICENSE
secudeps-0.1.0.dist-info/METADATA
secudeps-0.1.0.dist-info/WHEEL
secudeps-0.1.0.dist-info/entry_points.txt
secudeps-0.1.0.dist-info/top_level.txt
secudeps-0.1.0.dist-info/RECORD
