Metadata-Version: 2.1
Name: secudeps
Version: 0.1.0
Summary: A CLI tool to assess vulnerabilities in project dependencies
Home-page: https://gitlab.com/saber.bks/secudeps
Author: Saber Boukhriss
Author-email: saber@securas.fr
Classifier: Programming Language :: Python :: 3
Classifier: License :: OSI Approved :: MIT License
Classifier: Operating System :: OS Independent
Requires-Python: >=3.6
License-File: LICENSE
Requires-Dist: requests
Requires-Dist: pandas
Requires-Dist: click
